youqu_dogtail/__init__.py
youqu_dogtail/__version__.py
youqu_dogtail/conf.py
youqu_dogtail/install_depends.py
youqu_dogtail/dogtail/__init__.py
youqu_dogtail/dogtail/config.py
youqu_dogtail/dogtail/distro.py
youqu_dogtail/dogtail/dump.py
youqu_dogtail/dogtail/errors.py
youqu_dogtail/dogtail/i18n.py
youqu_dogtail/dogtail/logging.py
youqu_dogtail/dogtail/path.py
youqu_dogtail/dogtail/predicate.py
youqu_dogtail/dogtail/procedural.py
youqu_dogtail/dogtail/rawinput.py
youqu_dogtail/dogtail/sessions.py
youqu_dogtail/dogtail/tc.py
youqu_dogtail/dogtail/tree.py
youqu_dogtail/dogtail/utils.py
youqu_dogtail/dogtail/version.py
youqu_dogtail/dogtail/wrapped.py
youqu_dogtail-2024.6.27.dist-info/METADATA
youqu_dogtail-2024.6.27.dist-info/WHEEL
youqu_dogtail-2024.6.27.dist-info/licenses/LICENSE
youqu_dogtail-2024.6.27.dist-info/RECORD
