Metadata-Version: 2.1
Name: youqu-dogtail
Version: 2024.6.27
Author-email: mikigo <huangmingqiang@uniontech.com>
License: GPL2.0
License-File: LICENSE
Requires-Python: >=3.7
Requires-Dist: funnylog
